LICENSE
MANIFEST.in
README.rst
setup.py
django_plexauth.egg-info/PKG-INFO
django_plexauth.egg-info/SOURCES.txt
django_plexauth.egg-info/dependency_links.txt
django_plexauth.egg-info/requires.txt
django_plexauth.egg-info/top_level.txt
plexauth/__init__.py
plexauth/admin.py
plexauth/auth.py
plexauth/models.py
plexauth/tests.py
plexauth/urls.py
plexauth/views.py
plexauth/static/plexauth/custom.css
plexauth/templates/plexauth/base.html
plexauth/templates/plexauth/bootstrap.html
plexauth/templates/plexauth/index.html