Metadata-Version: 1.1
Name: django-plexauth
Version: 0.1.1
Summary: A django auth backend for authenticating against plex.tv
Home-page: https://github.com/munnerz/django-plexauth
Author: James Munnelly
Author-email: james@munnelly.eu
License: BSD License
Platform: UNKNOWN
Classifier: Environment :: Web Environment
Classifier: Framework :: Django
Classifier: Intended Audience :: Developers
Classifier: License :: OSI Approved :: BSD License
Classifier: Operating System :: OS Independent
Classifier: Programming Language :: Python
Classifier: Programming Language :: Python :: 3
Classifier: Programming Language :: Python :: 3.2
Classifier: Programming Language :: Python :: 3.3
Classifier: Topic :: Internet :: WWW/HTTP
Classifier: Topic :: Internet :: WWW/HTTP :: Dynamic Content
